crear_flask_app/__init__.py
crear_flask_app/__main__.py
crear_flask_app-0.1.dist-info/METADATA
crear_flask_app-0.1.dist-info/WHEEL
crear_flask_app-0.1.dist-info/entry_points.txt
crear_flask_app-0.1.dist-info/top_level.txt
crear_flask_app-0.1.dist-info/RECORD
